[
  {
    "name": "(None)",
    "AP": "(None)",
    "Drop": "(None)",
    "img": "https://cdn.discordapp.com/avatars/228126136192860160/39f75d83034c6b19776ece7e431a3c54.png"
  },
  {
    "name": "Hero's Proof (英雄の証)",
    "AP": "Okeanos - Pirate Ship\n海賊船\n[Map link](http://cirnopedia.org/quest_chapter_03.php)",
    "Drop": "America - Dallas\nダラス\n[Map link](http://cirnopedia.org/quest_chapter_05.php)",
    "img": "http://vignette1.wikia.nocookie.net/fategrandorder/images/a/a7/Heros_proof.png"
  },
  {
    "name": "Unlucky Bones (凶骨)",
    "AP": "Fuyuki - Unconfirmed Coordinate X-C\n未確認座標X-C\n[Map link](http://cirnopedia.org/quest_chapter_00.php)",
    "Drop": "Fuyuki - Unconfirmed Coordinate X-G\n未確認座標X-G\n[Map link](http://cirnopedia.org/quest_chapter_00.php)",
    "img": "http://vignette3.wikia.nocookie.net/fategrandorder/images/c/ca/Unlucky_bone.png"
  },
  {
    "name": "Dragon Fang (竜の牙)",
    "AP": "America - Deming\nデミング\n[Map link](http://cirnopedia.org/quest_chapter_05.php)",
    "Drop": "Babylonia - Eridu\nエリドゥ\n[Map link](http://cirnopedia.org/quest_chapter_07_free.php)",
    "img": "http://vignette2.wikia.nocookie.net/fategrandorder/images/6/6f/Dragon_fang.png"
  },
  {
    "name": "Void's Refuse (虚影の塵)",
    "AP": "America - Charlotte\nシャーロット\n[Map link](http://cirnopedia.org/quest_chapter_05.php)",
    "Drop": "America - Charlotte\nシャーロット\n[Map link](http://cirnopedia.org/quest_chapter_05.php)",
    "img": "http://vignette2.wikia.nocookie.net/fategrandorder/images/4/43/Voids_refuse.png"
  },
  {
    "name": "Chain of Fools (愚者の鎖)",
    "AP": "Camelot - Wilderness of Death\n死の荒野\n[Map link](http://cirnopedia.org/quest_chapter_06_free.php)",
    "Drop": "Camelot - Wilderness of Death\n死の荒野\n[Map link](http://cirnopedia.org/quest_chapter_06_free.php)",
    "img": "http://vignette4.wikia.nocookie.net/fategrandorder/images/5/55/Chains_of_The_Fool.png"
  },
  {
    "name": "Deadly Poison Stinger (万死の毒針)",
    "AP": "Babylonia - Field of Reeds\n葦の原\n[Map link](http://cirnopedia.org/quest_chapter_07_free.php)",
    "Drop": "Babylonia - Field of Reeds\n葦の原\n[Map link](http://cirnopedia.org/quest_chapter_07_free.php)",
    "img": "http://vignette2.wikia.nocookie.net/fategrandorder/images/c/cc/Stinger_of_Certain_Death.png"
  },
  {
    "name": "Yggdrasil Seed (世界樹の種)\n",
    "AP": "Babylonia - Abolished Metropolis Babylon\n廃都バビロン\n[Map link](http://cirnopedia.org/quest_chapter_07_free.php)",
    "Drop": "Babylonia - Abolished Metropolis Babylon\n廃都バビロン\n[Map link](http://cirnopedia.org/quest_chapter_07_free.php)",
    "img": "http://vignette1.wikia.nocookie.net/fategrandorder/images/4/41/Yggdrasil_seed.png"
  },
  {
    "name": "Ghost Lantern (ゴーストランタン)",
    "AP": "Babylonia - Cuthah\nクタ\n[Map link](http://cirnopedia.org/quest_chapter_07_free.php)",
    "Drop": "Babylonia - Cuthah\nクタ\n[Map link](http://cirnopedia.org/quest_chapter_07_free.php)",
    "img": "http://vignette1.wikia.nocookie.net/fategrandorder/images/b/b1/Ghost_lantern.png"
  },
  {
    "name": "Octuplet Twin Crystals (八連双晶)",
    "AP": "Camelot - Holy City Districts\n聖都市街\n[Map link](http://cirnopedia.org/quest_chapter_06_free.php)",
    "Drop": "Camelot - Holy City Districts\n聖都市街\n[Map link](http://cirnopedia.org/quest_chapter_06_free.php)",
    "img": "http://vignette2.wikia.nocookie.net/fategrandorder/images/8/84/Octuplet_twin_crystals.png"
  },
  {
    "name": "Snake Jewel (蛇の宝玉)\n",
    "AP": "Babylonia - Marshland\n湿原\n[Map link](http://cirnopedia.org/quest_chapter_07_free.php)",
    "Drop": "Chaldea (Fri) - Caster 30AP\n術上級",
    "img": "http://vignette3.wikia.nocookie.net/fategrandorder/images/2/28/Snake_jewel.png"
  },
  {
    "name": "Phoenix Plume (鳳凰の羽根)",
    "AP": "Chaldea (Sun) - Saber 30AP\n剣上級",
    "Drop": "Chaldea (Mon) - Archer 40AP\n弓超級",
    "img": "http://vignette2.wikia.nocookie.net/fategrandorder/images/c/c4/Phoenix_plume.png"
  },
  {
    "name": "Infinity Gear (無間の歯車)",
    "AP": "Shinjuku - Party Hall\nバレルタワー",
    "Drop": "Shinjuku - Party Hall\nバレルタワー",
    "img": "http://vignette1.wikia.nocookie.net/fategrandorder/images/d/d5/Infinity_gear.png"
  },
  {
    "name": "Forbidden Page (禁断の頁)",
    "AP": "Shinjuku - Shinjuku 2-chome\n新宿二丁目",
    "Drop": "Shinjuku - Shinjuku 2-chome\n新宿二丁目",
    "img": "http://vignette2.wikia.nocookie.net/fategrandorder/images/e/e6/Forbidden_page.png"
  },
  {
    "name": "Homunculus Baby (ホムンクルスベビー)",
    "AP": "London - Southwark\nサザーク\n[Map link](http://cirnopedia.org/quest_chapter_04.php)",
    "Drop": "London - Southwark\nサザーク\n[Map link](http://cirnopedia.org/quest_chapter_04.php)",
    "img": "http://vignette4.wikia.nocookie.net/fategrandorder/images/3/3c/Homunculus_baby.png"
  },
  {
    "name": "Meteoric Horseshoe (隕蹄鉄)",
    "AP": "Camelot - Vast Land of Nothingness\n無の大地\n[Map link](http://cirnopedia.org/quest_chapter_06_free.php)",
    "Drop": "Camelot - Vast Land of Nothingness\n無の大地\n[Map link](http://cirnopedia.org/quest_chapter_06_free.php)",
    "img": "http://vignette2.wikia.nocookie.net/fategrandorder/images/3/34/Meteoric_horseshoe.png"
  },
  {
    "name": "Great Knight Medal (大騎士勲章)",
    "AP": "Camelot - Sovereign Castle\n王城\n[Map link](http://cirnopedia.org/quest_chapter_06_free.php)",
    "Drop": "Camelot - Sovereign Castle\n王城\n[Map link](http://cirnopedia.org/quest_chapter_06_free.php)",
    "img": "http://vignette1.wikia.nocookie.net/fategrandorder/images/6/67/Medal_of_Great_Knight.png"
  },
  {
    "name": "Shell of Recollection (追憶の貝殻)",
    "AP": "Babylonia - Observatory\n観測所\n[Map link](http://cirnopedia.org/quest_chapter_07_free.php)",
    "Drop": "Babylonia - Observatory\n観測所\n[Map link](http://cirnopedia.org/quest_chapter_07_free.php)",
    "img": "http://vignette2.wikia.nocookie.net/fategrandorder/images/e/eb/Seashell.png"
  },
  {
    "name": "Chaos Claw (混沌の爪)",
    "AP": "America - Des Moines\nデモイン\n[Map link](http://cirnopedia.org/quest_chapter_05.php)",
    "Drop": "America - Des Moines\nデモイン\n[Map link](http://cirnopedia.org/quest_chapter_05.php)",
    "img": "http://vignette3.wikia.nocookie.net/fategrandorder/images/6/67/Talon_of_chaos.png"
  },
  {
    "name": "Heart of a Foreign God (蛮神の心臓)",
    "AP": "Shinjuku - Shinjuku Imperial Garden\n新宿御苑",
    "Drop": "Shinjuku - Shinjuku Imperial Garden\n新宿御苑",
    "img": "http://vignette2.wikia.nocookie.net/fategrandorder/images/e/ec/Heart_of_a_foreign_god.png"
  },
  {
    "name": "Dragon's Reverse Scale (竜の逆鱗)",
    "AP": "Babylonia - Nippur\nニップル\n[Map link](http://cirnopedia.org/quest_chapter_07_free.php)",
    "Drop": "Babylonia - Nippur\nニップル\n[Map link](http://cirnopedia.org/quest_chapter_07_free.php)",
    "img": "http://vignette1.wikia.nocookie.net/fategrandorder/images/c/c8/Dragons_reverse_scale.png"
  },
  {
    "name": "Spirit Root (精霊根)",
    "AP": "Camelot - Holy City Districts\n聖都市街\n[Map link](http://cirnopedia.org/quest_chapter_06_free.php)",
    "Drop": "Camelot - Holy City Districts\n聖都市街\n[Map link](http://cirnopedia.org/quest_chapter_06_free.php)",
    "img": "http://vignette3.wikia.nocookie.net/fategrandorder/images/7/7b/Spiritroot.png"
  },
  {
    "name": "War Horse's Small Horn (戦馬の幼角)",
    "AP": "Camelot - Eastern Village\n東の村\n[Map link](http://cirnopedia.org/quest_chapter_06_free.php)",
    "Drop": "Camelot - Eastern Village\n東の村\n[Map link](http://cirnopedia.org/quest_chapter_06_free.php)",
    "img": "http://vignette3.wikia.nocookie.net/fategrandorder/images/b/b9/Horsehorn.png"
  },
  {
    "name": "Tear Stone of Blood (血の涙石)",
    "AP": "Shinjuku - Shinjuku 2-chome\n新宿二丁目",
    "Drop": "Shinjuku - Shinjuku 2-chome\n新宿二丁目",
    "img": "http://vignette3.wikia.nocookie.net/fategrandorder/images/f/ff/Bloodtear.png"
  },
  {
    "name": "Magical Cerebrospinal Fluid (魔術髄液)",
    "AP": "Shinjuku - Shinjuku Station\n新宿駅",
    "Drop": "Shinjuku - Shinjuku Station\n新宿駅",
    "img": "http://vignette2.wikia.nocookie.net/fategrandorder/images/b/bc/Magical_Cerebrospinal_Fluid_icon.png"
  },
  {
    "name": "Black Tallow (黒獣脂)",
    "AP": "Babylonia - Northern Hill\n北の高台\n[Map link](http://cirnopedia.org/quest_chapter_07_free.php)",
    "Drop": "Babylonia - Northern Hill\n北の高台\n[Map link](http://cirnopedia.org/quest_chapter_07_free.php)",
    "img": "http://vignette1.wikia.nocookie.net/fategrandorder/images/4/49/Blacktallow.png"
  },
  {
    "name": "Lamp of Sealed Evil (封魔のランプ)",
    "AP": "Camelot - Concealed Village\n隠れ村\n[Map link](http://cirnopedia.org/quest_chapter_06_free.php)",
    "Drop": "Camelot - Concealed Village\n隠れ村\n[Map link](http://cirnopedia.org/quest_chapter_06_free.php)",
    "img": "http://vignette2.wikia.nocookie.net/fategrandorder/images/8/88/Lamp_of_Demon_Sealing.png"
  },
  {
    "name": "Scarab of Wisdom (智慧のスカラベ)",
    "AP": "Camelot - Great Temple\n大神殿\n[Map link](http://cirnopedia.org/quest_chapter_06_free.php)",
    "Drop": "Camelot - Great Temple\n大神殿\n[Map link](http://cirnopedia.org/quest_chapter_06_free.php)",
    "img": "http://vignette3.wikia.nocookie.net/fategrandorder/images/c/c2/Scarab_of_Wisdom.png"
  },
  {
    "name": "Primordial Lanugo (原初の産毛)",
    "AP": "Babylonia - Blood Fort Andromeda\n鮮血神殿\n[Map link](http://cirnopedia.org/quest_chapter_07_free.php)",
    "Drop": "Babylonia - Blood Fort Andromeda\n鮮血神殿\n[Map link](http://cirnopedia.org/quest_chapter_07_free.php)",
    "img": "http://vignette2.wikia.nocookie.net/fategrandorder/images/f/f6/Primordial_Lanugo.png"
  },
  {
    "name": "Cursed Beast Gallstone (呪獣胆石)",
    "AP": "Babylonia - Mount Ahvāz\nエビフ山\n[Map link](http://cirnopedia.org/quest_chapter_07_free.php)",
    "Drop": "Babylonia - Mount Ahvāz\nエビフ山\n[Map link](http://cirnopedia.org/quest_chapter_07_free.php)",
    "img": "http://vignette3.wikia.nocookie.net/fategrandorder/images/5/59/Cursed_Beast_Cholecyst.png"
  }
]